odoo8_addon_mass_mailing_keep_archives-8.0.0.0.0.99.dev10-py2.7-nspkg.pth
odoo8_addon_mass_mailing_keep_archives-8.0.0.0.0.99.dev10.dist-info/METADATA
odoo8_addon_mass_mailing_keep_archives-8.0.0.0.0.99.dev10.dist-info/RECORD
odoo8_addon_mass_mailing_keep_archives-8.0.0.0.0.99.dev10.dist-info/WHEEL
odoo8_addon_mass_mailing_keep_archives-8.0.0.0.0.99.dev10.dist-info/namespace_packages.txt
odoo8_addon_mass_mailing_keep_archives-8.0.0.0.0.99.dev10.dist-info/top_level.txt
odoo_addons/mass_mailing_keep_archives/README.rst
odoo_addons/mass_mailing_keep_archives/__init__.py
odoo_addons/mass_mailing_keep_archives/__openerp__.py
odoo_addons/mass_mailing_keep_archives/mass_mailing_view.xml
odoo_addons/mass_mailing_keep_archives/i18n/ca.po
odoo_addons/mass_mailing_keep_archives/i18n/de.po
odoo_addons/mass_mailing_keep_archives/i18n/es.po
odoo_addons/mass_mailing_keep_archives/i18n/es_CO.po
odoo_addons/mass_mailing_keep_archives/i18n/fi.po
odoo_addons/mass_mailing_keep_archives/i18n/fr.po
odoo_addons/mass_mailing_keep_archives/i18n/mass_mailing_keep_archives.pot
odoo_addons/mass_mailing_keep_archives/i18n/pt_BR.po
odoo_addons/mass_mailing_keep_archives/i18n/sl.po
odoo_addons/mass_mailing_keep_archives/models/__init__.py
odoo_addons/mass_mailing_keep_archives/models/mass_mailing.py
odoo_addons/mass_mailing_keep_archives/static/description/icon.png
