Metadata-Version: 2.1
Name: odoo8-addon-mass-mailing-keep-archives
Version: 8.0.0.0.0.99.dev10
Summary: Mass Mailing Keep Archives
Home-page: https://www.adhoc.com.ar/
Author: ADHOC SA, Odoo Community Association (OCA)
Author-email: support@odoo-community.org
License: AGPL-3
Platform: UNKNOWN
Classifier: Programming Language :: Python
Classifier: Framework :: Odoo
Classifier: License :: OSI Approved :: GNU Affero General Public License v3
Requires-Python: ~=2.7
Requires-Dist: odoo (<9.0a,>=8.0a)
